compas_fofin/__init__.py
compas_fofin/session.py
compas_fofin/settings.py
compas_fofin/conduits/__init__.py
compas_fofin/conduits/cablemeshconduit.py
compas_fofin/conversions/__init__.py
compas_fofin/conversions/cablemesh.py
compas_fofin/conversions/curves.py
compas_fofin/datastructures/__init__.py
compas_fofin/datastructures/cablemesh.py
compas_fofin/scene/__init__.py
compas_fofin/scene/cablemeshobject.py
compas_fofin/scene/constraintobject.py
compas_fofin/solvers/__init__.py
compas_fofin/solvers/autoupdatefd.py
compas_fofin/solvers/interactivemovefd.py
compas_fofin/solvers/interactivescalefd.py
compas_fofin-0.15.3.dist-info/licenses/AUTHORS.md
compas_fofin-0.15.3.dist-info/licenses/LICENSE
compas_fofin-0.15.3.dist-info/METADATA
compas_fofin-0.15.3.dist-info/WHEEL
compas_fofin-0.15.3.dist-info/top_level.txt
compas_fofin-0.15.3.dist-info/RECORD
