Metadata-Version: 2.4
Name: compas_fofin
Version: 0.15.3
Summary: COMPAS FormFinder
Author-email: tom van mele <tom.v.mele@gmail.com>
License: MIT License
Project-URL: Homepage, https://blockresearchgroup.github.io/compas_fofin
Project-URL: Documentation, https://blockresearchgroup.github.io/compas_fofin
Project-URL: Repository, https://github.com/blockresearchgroup/compas_fofin
Project-URL: Changelog, https://github.com/blockresearchgroup/compas_fofin/blob/main/CHANGELOG.md
Project-URL: Issues, https://github.com/blockresearchgroup/compas_fofin/issues
Project-URL: Forum, https://forum.compas-framework.org/
Classifier: Development Status :: 4 - Beta
Classifier: Topic :: Scientific/Engineering
Classifier: Operating System :: Unix
Classifier: Operating System :: POSIX
Classifier: Operating System :: Microsoft :: Windows
Classifier: Programming Language :: Python
Classifier: Programming Language :: Python :: 3
Classifier: Programming Language :: Python :: 3.9
Classifier: Programming Language :: Python :: 3.10
Classifier: Programming Language :: Python :: 3.11
Requires-Python: >=3.9
License-File: LICENSE
License-File: AUTHORS.md
Requires-Dist: compas>=2.9
Requires-Dist: compas_dr>=0.3
Requires-Dist: compas_fd>=0.5.2
Requires-Dist: compas_rui>=0.5.0
Requires-Dist: compas_session>=0.4.5
Provides-Extra: dev
Requires-Dist: attrs>=17.4; extra == "dev"
Requires-Dist: black>=22.12.0; extra == "dev"
Requires-Dist: bump-my-version; extra == "dev"
Requires-Dist: compas_invocations2; extra == "dev"
Requires-Dist: invoke>=0.14; extra == "dev"
Requires-Dist: ruff; extra == "dev"
Requires-Dist: sphinx_compas2_theme; extra == "dev"
Requires-Dist: twine; extra == "dev"
Requires-Dist: wheel; extra == "dev"
Dynamic: license-file
